serialenum.py
setup.py
serialenum.egg-info/PKG-INFO
serialenum.egg-info/SOURCES.txt
serialenum.egg-info/dependency_links.txt
serialenum.egg-info/entry_points.txt
serialenum.egg-info/not-zip-safe
serialenum.egg-info/requires.txt
serialenum.egg-info/top_level.txt