Metadata-Version: 1.1
Name: serialenum
Version: 0.3
Summary: Cross-platform serial port enumeration
Home-page: https://github.com/djs/serialenum
Author: Dan Savilonis
Author-email: djs@n-cube.org
License: BSD
Keywords: serial serial-port
Platform: UNKNOWN
Classifier: Development Status :: 4 - Beta
Classifier: Intended Audience :: Developers
Classifier: License :: OSI Approved :: BSD License
Classifier: Operating System :: Microsoft :: Windows
Classifier: Operating System :: POSIX :: Linux
Classifier: Programming Language :: Python
Classifier: Topic :: Software Development :: Libraries :: Python Modules
